libssa/README_GUI.md
libssa/__init__.py
libssa/libssa2.py
libssa/data/synthetic_samples_ultra-low-res-spectrometer_c-model.tar.gz
libssa/env/__init__.py
libssa/env/equations.py
libssa/env/export.py
libssa/env/functions.py
libssa/env/imports.py
libssa/env/spectra.py
libssa/env/config/__init__.py
libssa/env/config/ion.py
libssa/env/gui/__init__.py
libssa/env/gui/libssagui.py
libssa/env/gui/libssagui.ui
libssa/pic/libssa.svg
libssa/pic/examples/libs_spectrum.png
libssa/pic/examples/libssa.png
libssa/pic/examples/libssa_fluxogram.png
libssa/pic/examples/montage.png
libssa/pic/fonts/PTSans-BoldItalic.ttf
libssa/pic/icons/check-square-regular.svg
libssa/pic/icons/check-square-solid.svg
libssa/pic/icons/file-excel-regular.svg
libssa/pic/icons/file-excel-solid.svg
libssa/pic/icons/file-export-solid.svg
libssa/pic/icons/file-import-solid.svg
libssa/pic/icons/file-text-regular.svg
libssa/pic/icons/minus-square-regular.svg
libssa/pic/icons/minus-square-solid.svg
libssa/pic/icons/plus-square-regular.svg
libssa/pic/icons/plus-square-solid.svg
libssa/pic/icons/question-circle-regular.svg
libssa/pic/icons/table-solid.svg
libssa/pic/icons/times-circle-regular.svg
tests/test_export_areas.py
tests/test_load_spectra.py
tests/test_startup.py
libssa-2.5.0.dist-info/LICENSE.txt
libssa-2.5.0.dist-info/METADATA
libssa-2.5.0.dist-info/WHEEL
libssa-2.5.0.dist-info/entry_points.txt
libssa-2.5.0.dist-info/top_level.txt
libssa-2.5.0.dist-info/RECORD
