Metadata-Version: 2.1
Name: libssa
Version: 2.5.0
Summary: LIBSsa: an open source software for analyzing LIBS spectra
Author-email: Kleydson Stenio <9257942+kstenio@users.noreply.github.com>
License: GNU AFFERO GENERAL PUBLIC LICENSE
Project-URL: Homepage, https://github.com/kstenio/libssa
Project-URL: Documentation, https://kstenio.github.io/libssa/
Keywords: python,libs,spectroscopy
Classifier: License :: OSI Approved :: GNU Affero General Public License v3 or later (AGPLv3+)
Classifier: Operating System :: OS Independent
Classifier: Programming Language :: Python :: 3.9
Classifier: Programming Language :: Python :: 3.10
Classifier: Programming Language :: Python :: 3.11
Requires-Python: <3.12,>=3.9
License-File: LICENSE.txt
Requires-Dist: markdown <=3.4.3
Requires-Dist: numpy <=1.25.1
Requires-Dist: openpyxl <=3.1.2
Requires-Dist: pandas <=2.0.3
Requires-Dist: psutil <=5.9.5
Requires-Dist: pyqtgraph <=0.13.3
Requires-Dist: pyside6 <=6.4.3
Requires-Dist: scikit-learn <=1.3.0
Requires-Dist: scipy <=1.11.1
